capitalonline/__init__.py
capitalonline/common/__init__.py
capitalonline/common/abstract_client.py
capitalonline/common/client.py
capitalonline/common/credential.py
capitalonline/common/sign.py
capitalonline/common/exception/__init__.py
capitalonline/common/exception/cds_sdk_exception.py
capitalonline/common/http/__init__.py
capitalonline/common/http/request.py
capitalonline/common/profile/__init__.py
capitalonline/common/profile/client_profile.py
capitalonline/common/profile/http_profile.py
capitalonline/haproxy/__init__.py
capitalonline/haproxy/client.py
capitalonline/haproxy/client_test.py
capitalonline/haproxy/models.py
capitalonline/instance/__init__.py
capitalonline/instance/client.py
capitalonline/instance/client_test.py
capitalonline/instance/models.py
capitalonline/vdc/__init__.py
capitalonline/vdc/client.py
capitalonline/vdc/client_test.py
capitalonline/vdc/model.py
cds_python_sdk-0.14.dist-info/LICENSE
cds_python_sdk-0.14.dist-info/METADATA
cds_python_sdk-0.14.dist-info/WHEEL
cds_python_sdk-0.14.dist-info/top_level.txt
cds_python_sdk-0.14.dist-info/RECORD
