Metadata-Version: 2.1
Name: cds-python-sdk
Version: 0.14
Summary: 首云python SDK
Home-page: http://capitalonline.net/
Author: capitalonline
License-File: LICENSE
